average_color.py
average_color-0.1.1.dist-info/METADATA
average_color-0.1.1.dist-info/WHEEL
average_color-0.1.1.dist-info/entry_points.txt
average_color-0.1.1.dist-info/licenses/LICENSE
average_color-0.1.1.dist-info/RECORD
