Metadata-Version: 2.3
Name: average-color
Version: 0.1.1
Summary: Prints the average hex color of an image.
Project-URL: Homepage, https://github.com/Samathingamajig/average-color
Project-URL: Documentation, https://github.com/Samathingamajig/average-color/blob/master/README.md
Project-URL: Repository, https://github.com/Samathingamajig/average-color
Project-URL: Bug Tracker, https://github.com/Samathingamajig/average-color/issues
Author-email: Samuel Gunter <samathingamajig@gmail.com>
License: MIT License
License-File: LICENSE
Keywords: average,color,image
Classifier: Programming Language :: Python
Requires-Python: >=3.8
Requires-Dist: pillow
